Workbook

Sheet README
A1: MarkOS AI -- Campaign Performance Dummy Dataset
A2: Illustrative sample data built for the MarkOS AI portfolio project -- not a real business. See the live site: https://milindw1612.github.io/markos-ai/
A4: Products in this workbook
A5: Product | B5: Industry | C5: Funnel Type | D5: Channels | E5: Website (dummy)
A6: Vantage CRM | B6: SaaS / B2B Tech | C6: B2B | D6: LinkedIn | E6: vantagecrm.example.com
A7: Lumiere Skincare | B7: Beauty / Cosmetics | C7: B2C | D7: Instagram, Facebook, Pinterest | E7: lumiereskincare.example.com
A8: Solara Fitband | B8: Consumer Electronics / Wearables | C8: B2C | D8: Google Ads, Facebook | E8: solarafitband.example.com
A9: Aurelia Jewellery | B9: Luxury / Jewellery | C9: B2C | D9: Instagram, Pinterest, Google Ads | E9: aureliajewellery.example.com
A11: Campaign windows
A12: Current campaign: Aug 1, 2026 - Aug 31, 2026 (31 days)
A13: Historical comparison campaign (previous quarter): May 1, 2026 - May 31, 2026 (31 days)
A15: Column definitions (Sheets: Daily Performance - Current / Historical)
A16: Date | B16: Calendar day of activity
A17: Product / Industry / Funnel Type | B17: Which product, its industry, and whether it follows a B2B or B2C conversion funnel
A18: Channel | B18: Ad platform the spend/results are attributed to
A19: Website | B19: Dummy landing-page domain for this product (uses the .example reserved domain -- not a real, live site)
A20: Spend | B20: Media spend for that channel that day, local currency
A21: Impressions / Clicks / CTR | B21: Reach and click-through; CTR = Clicks / Impressions
A22: Website Visits | B22: Sessions landing on the dummy website from this channel
A23: Leads | B23: Top-of-funnel contact captured (form fill, sign-up, etc.) -- tracked for every product
A24: MQL / SQL / Bookings (INR) | B24: B2B-only (Vantage CRM): Marketing Qualified Lead, Sales Qualified Lead, and closed contract value. 'N/A' for B2C products.
A25: Conversions | B25: B2C-only: a completed purchase/order. 'N/A' for the B2B product (Vantage CRM), which uses Bookings instead.
A26: CAC | B26: Customer Acquisition Cost = Spend / Leads
A27: Revenue | B27: Attributed revenue for that channel that day (bookings-derived for Vantage CRM, order-value-derived for the other three)
A28: ROAS | B28: Return on Ad Spend = Revenue / Spend

Sheet Campaign Overview
A1: Product | B1: Industry | C1: Campaign Name | D1: Start Date | E1: End Date | F1: Channels | G1: Total Budget (Current, INR) | H1: Website URL | I1: Creative Types Used
A2: Vantage CRM | B2: SaaS / B2B Tech | C2: Vantage CRM -- August Growth Push | D2: 46235 | E2: 46265 | F2: LinkedIn | G2: =SUMIF('Daily Performance - Current'!$B:$B,A2,'Daily Performance - Current'!$G:$G) | H2: vantagecrm.example.com | I2: Text 45%, Image 35%, Video 20%
A3: Lumiere Skincare | B3: Beauty / Cosmetics | C3: Lumiere Skincare -- August Growth Push | D3: 46235 | E3: 46265 | F3: Instagram, Facebook, Pinterest | G3: =SUMIF('Daily Performance - Current'!$B:$B,A3,'Daily Performance - Current'!$G:$G) | H3: lumiereskincare.example.com | I3: Text 20%, Image 40%, Video 40%
A4: Solara Fitband | B4: Consumer Electronics / Wearables | C4: Solara Fitband -- August Growth Push | D4: 46235 | E4: 46265 | F4: Google Ads, Facebook | G4: =SUMIF('Daily Performance - Current'!$B:$B,A4,'Daily Performance - Current'!$G:$G) | H4: solarafitband.example.com | I4: Text 20%, Image 35%, Video 45%
A5: Aurelia Jewellery | B5: Luxury / Jewellery | C5: Aurelia Jewellery -- August Growth Push | D5: 46235 | E5: 46265 | F5: Instagram, Pinterest, Google Ads | G5: =SUMIF('Daily Performance - Current'!$B:$B,A5,'Daily Performance - Current'!$G:$G) | H5: aureliajewellery.example.com | I5: Text 15%, Image 40%, Video 45%

Sheet Daily Performance - Current
A1: Date | B1: Product | C1: Industry | D1: Funnel Type | E1: Channel | F1: Website | G1: Spend | H1: Impressions | I1: Clicks | J1: CTR | K1: Website Visits | L1: Leads | M1: MQL | N1: SQL | O1: Bookings (INR) | P1: Conversions | Q1: CAC | R1: Revenue | S1: ROAS
A2: 46235 | B2: Vantage CRM | C2: SaaS / B2B Tech | D2: B2B | E2: LinkedIn | F2: vantagecrm.example.com | G2: 3677 | H2: 4082 | I2: 86 | J2: =I2/H2 | K2: 82 | L2: 3 | M2: 3 | N2: 3 | O2: 42000 | P2: N/A | Q2: =IFERROR(G2/L2,0) | R2: 45090 | S2: =IFERROR(R2/G2,0)
A3: 46236 | B3: Vantage CRM | C3: SaaS / B2B Tech | D3: B2B | E3: LinkedIn | F3: vantagecrm.example.com | G3: 3338 | H3: 0 | I3: 0 | J3: =I3/H3 | K3: 0 | L3: 0 | M3: 0 | N3: 0 | O3: 0 | P3: N/A | Q3: =IFERROR(G3/L3,0) | R3: 0 | S3: =IFERROR(R3/G3,0)
A4: 46237 | B4: Vantage CRM | C4: SaaS / B2B Tech | D4: B2B | E4: LinkedIn | F4: vantagecrm.example.com | G4: 3789 | H4: 1361 | I4: 29 | J4: =I4/H4 | K4: 26 | L4: 1 | M4: 1 | N4: 0 | O4: 0 | P4: N/A | Q4: =IFERROR(G4/L4,0) | R4: 0 | S4: =IFERROR(R4/G4,0)
A5: 46238 | B5: Vantage CRM | C5: SaaS / B2B Tech | D5: B2B | E5: LinkedIn | F5: vantagecrm.example.com | G5: 3837 | H5: 4082 | I5: 86 | J5: =I5/H5 | K5: 80 | L5: 3 | M5: 3 | N5: 0 | O5: 0 | P5: N/A | Q5: =IFERROR(G5/L5,0) | R5: 0 | S5: =IFERROR(R5/G5,0)
A6: 46239 | B6: Vantage CRM | C6: SaaS / B2B Tech | D6: B2B | E6: LinkedIn | F6: vantagecrm.example.com | G6: 3108 | H6: 1361 | I6: 29 | J6: =I6/H6 | K6: 28 | L6: 1 | M6: 1 | N6: 1 | O6: 0 | P6: N/A | Q6: =IFERROR(G6/L6,0) | R6: 0 | S6: =IFERROR(R6/G6,0)
A7: 46240 | B7: Vantage CRM | C7: SaaS / B2B Tech | D7: B2B | E7: LinkedIn | F7: vantagecrm.example.com | G7: 3272 | H7: 5442 | I7: 114 | J7: =I7/H7 | K7: 106 | L7: 4 | M7: 4 | N7: 2 | O7: 42000 | P7: N/A | Q7: =IFERROR(G7/L7,0) | R7: 45559 | S7: =IFERROR(R7/G7,0)
A8: 46241 | B8: Vantage CRM | C8: SaaS / B2B Tech | D8: B2B | E8: LinkedIn | F8: vantagecrm.example.com | G8: 3632 | H8: 2721 | I8: 57 | J8: =I8/H8 | K8: 52 | L8: 2 | M8: 2 | N8: 2 | O8: 0 | P8: N/A | Q8: =IFERROR(G8/L8,0) | R8: 0 | S8: =IFERROR(R8/G8,0)
A9: 46242 | B9: Vantage CRM | C9: SaaS / B2B Tech | D9: B2B | E9: LinkedIn | F9: vantagecrm.example.com | G9: 3520 | H9: 0 | I9: 0 | J9: =I9/H9 | K9: 0 | L9: 0 | M9: 0 | N9: 0 | O9: 0 | P9: N/A | Q9: =IFERROR(G9/L9,0) | R9: 0 | S9: =IFERROR(R9/G9,0)
A10: 46243 | B10: Vantage CRM | C10: SaaS / B2B Tech | D10: B2B | E10: LinkedIn | F10: vantagecrm.example.com | G10: 3596 | H10: 2721 | I10: 57 | J10: =I10/H10 | K10: 52 | L10: 2 | M10: 2 | N10: 2 | O10: 0 | P10: N/A | Q10: =IFERROR(G10/L10,0) | R10: 0 | S10: =IFERROR(R10/G10,0)
A11: 46244 | B11: Vantage CRM | C11: SaaS / B2B Tech | D11: B2B | E11: LinkedIn | F11: vantagecrm.example.com | G11: 3385 | H11: 1361 | I11: 29 | J11: =I11/H11 | K11: 27 | L11: 1 | M11: 1 | N11: 0 | O11: 0 | P11: N/A | Q11: =IFERROR(G11/L11,0) | R11: 0 | S11: =IFERROR(R11/G11,0)
A12: 46245 | B12: Vantage CRM | C12: SaaS / B2B Tech | D12: B2B | E12: LinkedIn | F12: vantagecrm.example.com | G12: 3822 | H12: 4082 | I12: 86 | J12: =I12/H12 | K12: 83 | L12: 3 | M12: 3 | N12: 3 | O12: 42000 | P12: N/A | Q12: =IFERROR(G12/L12,0) | R12: 40960 | S12: =IFERROR(R12/G12,0)
A13: 46246 | B13: Vantage CRM | C13: SaaS / B2B Tech | D13: B2B | E13: LinkedIn | F13: vantagecrm.example.com | G13: 3796 | H13: 2721 | I13: 57 | J13: =I13/H13 | K13: 52 | L13: 2 | M13: 2 | N13: 1 | O13: 0 | P13: N/A | Q13: =IFERROR(G13/L13,0) | R13: 0 | S13: =IFERROR(R13/G13,0)
... A32: 46265 | B32: Vantage CRM | C32: SaaS / B2B Tech | D32: B2B | E32: LinkedIn | F32: vantagecrm.example.com | G32: 4140 | H32: 2721 | I32: 57 | J32: =I32/H32 | K32: 50 | L32: 2 | M32: 2 | N32: 0 | O32: 0 | P32: N/A | Q32: =IFERROR(G32/L32,0) | R32: 0 | S32: =IFERROR(R32/G32,0)
A33: 46235 | B33: Lumiere Skincare | C33: Beauty / Cosmetics | D33: B2C | E33: Instagram | F33: lumiereskincare.example.com | G33: 4229 | H33: 18683 | I33: 392 | J33: =I33/H33 | K33: 338 | L33: 10 | M33: N/A | N33: N/A | O33: N/A | P33: 10 | Q33: =IFERROR(G33/L33,0) | R33: 14792 | S33: =IFERROR(R33/G33,0)
A34: 46236 | B34: Lumiere Skincare | C34: Beauty / Cosmetics | D34: B2C | E34: Instagram | F34: lumiereskincare.example.com | G34: 4545 | H34: 21106 | I34: 443 | J34: =I34/H34 | K34: 431 | L34: 12 | M34: N/A | N34: N/A | O34: N/A | P34: 12 | Q34: =IFERROR(G34/L34,0) | R34: 16709 | S34: =IFERROR(R34/G34,0)
A35: 46237 | B35: Lumiere Skincare | C35: Beauty / Cosmetics | D35: B2C | E35: Instagram | F35: lumiereskincare.example.com | G35: 4712 | H35: 22187 | I35: 466 | J35: =I35/H35 | K35: 404 | L35: 12 | M35: N/A | N35: N/A | O35: N/A | P35: 12 | Q35: =IFERROR(G35/L35,0) | R35: 17565 | S35: =IFERROR(R35/G35,0)
A36: 46238 | B36: Lumiere Skincare | C36: Beauty / Cosmetics | D36: B2C | E36: Instagram | F36: lumiereskincare.example.com | G36: 4448 | H36: 19323 | I36: 406 | J36: =I36/H36 | K36: 395 | L36: 11 | M36: N/A | N36: N/A | O36: N/A | P36: 11 | Q36: =IFERROR(G36/L36,0) | R36: 15298 | S36: =IFERROR(R36/G36,0)
A37: 46239 | B37: Lumiere Skincare | C37: Beauty / Cosmetics | D37: B2C | E37: Instagram | F37: lumiereskincare.example.com | G37: 4508 | H37: 16179 | I37: 340 | J37: =I37/H37 | K37: 324 | L37: 9 | M37: N/A | N37: N/A | O37: N/A | P37: 9 | Q37: =IFERROR(G37/L37,0) | R37: 12809 | S37: =IFERROR(R37/G37,0)
A38: 46240 | B38: Lumiere Skincare | C38: Beauty / Cosmetics | D38: B2C | E38: Instagram | F38: lumiereskincare.example.com | G38: 4416 | H38: 20872 | I38: 438 | J38: =I38/H38 | K38: 406 | L38: 11 | M38: N/A | N38: N/A | O38: N/A | P38: 11 | Q38: =IFERROR(G38/L38,0) | R38: 16525 | S38: =IFERROR(R38/G38,0)
A39: 46241 | B39: Lumiere Skincare | C39: Beauty / Cosmetics | D39: B2C | E39: Instagram | F39: lumiereskincare.example.com | G39: 4400 | H39: 24155 | I39: 507 | J39: =I39/H39 | K39: 483 | L39: 13 | M39: N/A | N39: N/A | O39: N/A | P39: 13 | Q39: =IFERROR(G39/L39,0) | R39: 19123 | S39: =IFERROR(R39/G39,0)
A40: 46242 | B40: Lumiere Skincare | C40: Beauty / Cosmetics | D40: B2C | E40: Instagram | F40: lumiereskincare.example.com | G40: 4178 | H40: 15500 | I40: 326 | J40: =I40/H40 | K40: 310 | L40: 8 | M40: N/A | N40: N/A | O40: N/A | P40: 8 | Q40: =IFERROR(G40/L40,0) | R40: 12272 | S40: =IFERROR(R40/G40,0)
A41: 46243 | B41: Lumiere Skincare | C41: Beauty / Cosmetics | D41: B2C | E41: Instagram | F41: lumiereskincare.example.com | G41: 4497 | H41: 22571 | I41: 474 | J41: =I41/H41 | K41: 461 | L41: 12 | M41: N/A | N41: N/A | O41: N/A | P41: 12 | Q41: =IFERROR(G41/L41,0) | R41: 17869 | S41: =IFERROR(R41/G41,0)
A42: 46244 | B42: Lumiere Skincare | C42: Beauty / Cosmetics | D42: B2C | E42: Instagram | F42: lumiereskincare.example.com | G42: 4370 | H42: 19088 | I42: 401 | J42: =I42/H42 | K42: 354 | L42: 10 | M42: N/A | N42: N/A | O42: N/A | P42: 10 | Q42: =IFERROR(G42/L42,0) | R42: 15112 | S42: =IFERROR(R42/G42,0)
A43: 46245 | B43: Lumiere Skincare | C43: Beauty / Cosmetics | D43: B2C | E43: Instagram | F43: lumiereskincare.example.com | G43: 5045 | H43: 22770 | I43: 478 | J43: =I43/H43 | K43: 443 | L43: 12 | M43: N/A | N43: N/A | O43: N/A | P43: 12 | Q43: =IFERROR(G43/L43,0) | R43: 18027 | S43: =IFERROR(R43/G43,0)
A44: 46246 | B44: Lumiere Skincare | C44: Beauty / Cosmetics | D44: B2C | E44: Instagram | F44: lumiereskincare.example.com | G44: 4885 | H44: 19405 | I44: 408 | J44: =I44/H44 | K44: 351 | L44: 11 | M44: N/A | N44: N/A | O44: N/A | P44: 11 | Q44: =IFERROR(G44/L44,0) | R44: 15363 | S44: =IFERROR(R44/G44,0)
... A280: 46265 | B280: Aurelia Jewellery | C280: Luxury / Jewellery | D280: B2C | E280: Google Ads | F280: aureliajewellery.example.com | G280: 3349 | H280: 1350 | I280: 28 | J280: =I280/H280 | K280: 26 | L280: 1 | M280: N/A | N280: N/A | O280: N/A | P280: 1 | Q280: =IFERROR(G280/L280,0) | R280: 14547 | S280: =IFERROR(R280/G280,0)

Sheet Daily Performance - Historical
A1: Date | B1: Product | C1: Industry | D1: Funnel Type | E1: Channel | F1: Website | G1: Spend | H1: Impressions | I1: Clicks | J1: CTR | K1: Website Visits | L1: Leads | M1: MQL | N1: SQL | O1: Bookings (INR) | P1: Conversions | Q1: CAC | R1: Revenue | S1: ROAS
A2: 46143 | B2: Vantage CRM | C2: SaaS / B2B Tech | D2: B2B | E2: LinkedIn | F2: vantagecrm.example.com | G2: 3226 | H2: 2721 | I2: 57 | J2: =I2/H2 | K2: 55 | L2: 2 | M2: 2 | N2: 2 | O2: 0 | P2: N/A | Q2: =IFERROR(G2/L2,0) | R2: 0 | S2: =IFERROR(R2/G2,0)
A3: 46144 | B3: Vantage CRM | C3: SaaS / B2B Tech | D3: B2B | E3: LinkedIn | F3: vantagecrm.example.com | G3: 3301 | H3: 4082 | I3: 86 | J3: =I3/H3 | K3: 75 | L3: 3 | M3: 3 | N3: 0 | O3: 0 | P3: N/A | Q3: =IFERROR(G3/L3,0) | R3: 0 | S3: =IFERROR(R3/G3,0)
A4: 46145 | B4: Vantage CRM | C4: SaaS / B2B Tech | D4: B2B | E4: LinkedIn | F4: vantagecrm.example.com | G4: 3551 | H4: 1361 | I4: 29 | J4: =I4/H4 | K4: 28 | L4: 1 | M4: 1 | N4: 1 | O4: 0 | P4: N/A | Q4: =IFERROR(G4/L4,0) | R4: 0 | S4: =IFERROR(R4/G4,0)
A5: 46146 | B5: Vantage CRM | C5: SaaS / B2B Tech | D5: B2B | E5: LinkedIn | F5: vantagecrm.example.com | G5: 3401 | H5: 2721 | I5: 57 | J5: =I5/H5 | K5: 52 | L5: 2 | M5: 2 | N5: 1 | O5: 0 | P5: N/A | Q5: =IFERROR(G5/L5,0) | R5: 0 | S5: =IFERROR(R5/G5,0)
A6: 46147 | B6: Vantage CRM | C6: SaaS / B2B Tech | D6: B2B | E6: LinkedIn | F6: vantagecrm.example.com | G6: 3481 | H6: 1361 | I6: 29 | J6: =I6/H6 | K6: 26 | L6: 1 | M6: 1 | N6: 0 | O6: 0 | P6: N/A | Q6: =IFERROR(G6/L6,0) | R6: 0 | S6: =IFERROR(R6/G6,0)
A7: 46148 | B7: Vantage CRM | C7: SaaS / B2B Tech | D7: B2B | E7: LinkedIn | F7: vantagecrm.example.com | G7: 3559 | H7: 4082 | I7: 86 | J7: =I7/H7 | K7: 84 | L7: 3 | M7: 3 | N7: 2 | O7: 0 | P7: N/A | Q7: =IFERROR(G7/L7,0) | R7: 0 | S7: =IFERROR(R7/G7,0)
A8: 46149 | B8: Vantage CRM | C8: SaaS / B2B Tech | D8: B2B | E8: LinkedIn | F8: vantagecrm.example.com | G8: 3311 | H8: 2721 | I8: 57 | J8: =I8/H8 | K8: 51 | L8: 2 | M8: 2 | N8: 2 | O8: 42000 | P8: N/A | Q8: =IFERROR(G8/L8,0) | R8: 46833 | S8: =IFERROR(R8/G8,0)
A9: 46150 | B9: Vantage CRM | C9: SaaS / B2B Tech | D9: B2B | E9: LinkedIn | F9: vantagecrm.example.com | G9: 3580 | H9: 2721 | I9: 57 | J9: =I9/H9 | K9: 52 | L9: 2 | M9: 2 | N9: 2 | O9: 0 | P9: N/A | Q9: =IFERROR(G9/L9,0) | R9: 0 | S9: =IFERROR(R9/G9,0)
A10: 46151 | B10: Vantage CRM | C10: SaaS / B2B Tech | D10: B2B | E10: LinkedIn | F10: vantagecrm.example.com | G10: 3490 | H10: 2721 | I10: 57 | J10: =I10/H10 | K10: 53 | L10: 2 | M10: 2 | N10: 0 | O10: 0 | P10: N/A | Q10: =IFERROR(G10/L10,0) | R10: 0 | S10: =IFERROR(R10/G10,0)
A11: 46152 | B11: Vantage CRM | C11: SaaS / B2B Tech | D11: B2B | E11: LinkedIn | F11: vantagecrm.example.com | G11: 3106 | H11: 8163 | I11: 171 | J11: =I11/H11 | K11: 149 | L11: 6 | M11: 6 | N11: 2 | O11: 0 | P11: N/A | Q11: =IFERROR(G11/L11,0) | R11: 0 | S11: =IFERROR(R11/G11,0)
A12: 46153 | B12: Vantage CRM | C12: SaaS / B2B Tech | D12: B2B | E12: LinkedIn | F12: vantagecrm.example.com | G12: 3743 | H12: 1361 | I12: 29 | J12: =I12/H12 | K12: 25 | L12: 1 | M12: 1 | N12: 1 | O12: 0 | P12: N/A | Q12: =IFERROR(G12/L12,0) | R12: 0 | S12: =IFERROR(R12/G12,0)
A13: 46154 | B13: Vantage CRM | C13: SaaS / B2B Tech | D13: B2B | E13: LinkedIn | F13: vantagecrm.example.com | G13: 3281 | H13: 4082 | I13: 86 | J13: =I13/H13 | K13: 75 | L13: 3 | M13: 3 | N13: 1 | O13: 42000 | P13: N/A | Q13: =IFERROR(G13/L13,0) | R13: 40580 | S13: =IFERROR(R13/G13,0)
... A32: 46173 | B32: Vantage CRM | C32: SaaS / B2B Tech | D32: B2B | E32: LinkedIn | F32: vantagecrm.example.com | G32: 3448 | H32: 2721 | I32: 57 | J32: =I32/H32 | K32: 51 | L32: 2 | M32: 2 | N32: 1 | O32: 0 | P32: N/A | Q32: =IFERROR(G32/L32,0) | R32: 0 | S32: =IFERROR(R32/G32,0)
A33: 46143 | B33: Lumiere Skincare | C33: Beauty / Cosmetics | D33: B2C | E33: Instagram | F33: lumiereskincare.example.com | G33: 4711 | H33: 19619 | I33: 412 | J33: =I33/H33 | K33: 359 | L33: 11 | M33: N/A | N33: N/A | O33: N/A | P33: 11 | Q33: =IFERROR(G33/L33,0) | R33: 15532 | S33: =IFERROR(R33/G33,0)
A34: 46144 | B34: Lumiere Skincare | C34: Beauty / Cosmetics | D34: B2C | E34: Instagram | F34: lumiereskincare.example.com | G34: 4058 | H34: 15691 | I34: 330 | J34: =I34/H34 | K34: 309 | L34: 9 | M34: N/A | N34: N/A | O34: N/A | P34: 9 | Q34: =IFERROR(G34/L34,0) | R34: 12423 | S34: =IFERROR(R34/G34,0)
A35: 46145 | B35: Lumiere Skincare | C35: Beauty / Cosmetics | D35: B2C | E35: Instagram | F35: lumiereskincare.example.com | G35: 4494 | H35: 16131 | I35: 339 | J35: =I35/H35 | K35: 305 | L35: 9 | M35: N/A | N35: N/A | O35: N/A | P35: 9 | Q35: =IFERROR(G35/L35,0) | R35: 12771 | S35: =IFERROR(R35/G35,0)
A36: 46146 | B36: Lumiere Skincare | C36: Beauty / Cosmetics | D36: B2C | E36: Instagram | F36: lumiereskincare.example.com | G36: 4229 | H36: 15265 | I36: 321 | J36: =I36/H36 | K36: 298 | L36: 8 | M36: N/A | N36: N/A | O36: N/A | P36: 8 | Q36: =IFERROR(G36/L36,0) | R36: 12085 | S36: =IFERROR(R36/G36,0)
A37: 46147 | B37: Lumiere Skincare | C37: Beauty / Cosmetics | D37: B2C | E37: Instagram | F37: lumiereskincare.example.com | G37: 4434 | H37: 12509 | I37: 263 | J37: =I37/H37 | K37: 225 | L37: 7 | M37: N/A | N37: N/A | O37: N/A | P37: 7 | Q37: =IFERROR(G37/L37,0) | R37: 9903 | S37: =IFERROR(R37/G37,0)
A38: 46148 | B38: Lumiere Skincare | C38: Beauty / Cosmetics | D38: B2C | E38: Instagram | F38: lumiereskincare.example.com | G38: 4069 | H38: 15894 | I38: 334 | J38: =I38/H38 | K38: 304 | L38: 9 | M38: N/A | N38: N/A | O38: N/A | P38: 9 | Q38: =IFERROR(G38/L38,0) | R38: 12583 | S38: =IFERROR(R38/G38,0)
A39: 46149 | B39: Lumiere Skincare | C39: Beauty / Cosmetics | D39: B2C | E39: Instagram | F39: lumiereskincare.example.com | G39: 4185 | H39: 17469 | I39: 367 | J39: =I39/H39 | K39: 337 | L39: 10 | M39: N/A | N39: N/A | O39: N/A | P39: 10 | Q39: =IFERROR(G39/L39,0) | R39: 13830 | S39: =IFERROR(R39/G39,0)
A40: 46150 | B40: Lumiere Skincare | C40: Beauty / Cosmetics | D40: B2C | E40: Instagram | F40: lumiereskincare.example.com | G40: 4166 | H40: 12802 | I40: 269 | J40: =I40/H40 | K40: 236 | L40: 7 | M40: N/A | N40: N/A | O40: N/A | P40: 7 | Q40: =IFERROR(G40/L40,0) | R40: 10135 | S40: =IFERROR(R40/G40,0)
A41: 46151 | B41: Lumiere Skincare | C41: Beauty / Cosmetics | D41: B2C | E41: Instagram | F41: lumiereskincare.example.com | G41: 3954 | H41: 13794 | I41: 290 | J41: =I41/H41 | K41: 251 | L41: 8 | M41: N/A | N41: N/A | O41: N/A | P41: 8 | Q41: =IFERROR(G41/L41,0) | R41: 10921 | S41: =IFERROR(R41/G41,0)
A42: 46152 | B42: Lumiere Skincare | C42: Beauty / Cosmetics | D42: B2C | E42: Instagram | F42: lumiereskincare.example.com | G42: 4395 | H42: 14340 | I42: 301 | J42: =I42/H42 | K42: 263 | L42: 8 | M42: N/A | N42: N/A | O42: N/A | P42: 8 | Q42: =IFERROR(G42/L42,0) | R42: 11353 | S42: =IFERROR(R42/G42,0)
A43: 46153 | B43: Lumiere Skincare | C43: Beauty / Cosmetics | D43: B2C | E43: Instagram | F43: lumiereskincare.example.com | G43: 4391 | H43: 14712 | I43: 309 | J43: =I43/H43 | K43: 276 | L43: 8 | M43: N/A | N43: N/A | O43: N/A | P43: 8 | Q43: =IFERROR(G43/L43,0) | R43: 11647 | S43: =IFERROR(R43/G43,0)
A44: 46154 | B44: Lumiere Skincare | C44: Beauty / Cosmetics | D44: B2C | E44: Instagram | F44: lumiereskincare.example.com | G44: 4375 | H44: 16683 | I44: 350 | J44: =I44/H44 | K44: 302 | L44: 9 | M44: N/A | N44: N/A | O44: N/A | P44: 9 | Q44: =IFERROR(G44/L44,0) | R44: 13208 | S44: =IFERROR(R44/G44,0)
... A280: 46173 | B280: Aurelia Jewellery | C280: Luxury / Jewellery | D280: B2C | E280: Google Ads | F280: aureliajewellery.example.com | G280: 2953 | H280: 1081 | I280: 23 | J280: =I280/H280 | K280: 19 | L280: 0 | M280: N/A | N280: N/A | O280: N/A | P280: 0 | Q280: =IFERROR(G280/L280,0) | R280: 11647 | S280: =IFERROR(R280/G280,0)

Sheet Creative Performance
A1: Product | B1: Channel | C1: Creative Type | D1: Mix % of Spend | E1: Impressions | F1: Clicks | G1: CTR | H1: Conversions/Leads | I1: Notes
A2: Vantage CRM | B2: LinkedIn | C2: Text | D2: 0.45 | E2: =SUMIFS('Daily Performance - Current'!$H:$H,'Daily Performance - Current'!$B:$B,A2,'Daily Performance - Current'!$E:$E,B2)*D2 | F2: =SUMIFS('Daily Performance - Current'!$I:$I,'Daily Performance - Current'!$B:$B,A2,'Daily Performance - Current'!$E:$E,B2)*D2 | G2: =IFERROR(F2/E2,0) | H2: =SUMIFS('Daily Performance - Current'!$L:$L,'Daily Performance - Current'!$B:$B,A2,'Daily Performance - Current'!$E:$E,B2)*D2
A3: Vantage CRM | B3: LinkedIn | C3: Image | D3: 0.35 | E3: =SUMIFS('Daily Performance - Current'!$H:$H,'Daily Performance - Current'!$B:$B,A3,'Daily Performance - Current'!$E:$E,B3)*D3 | F3: =SUMIFS('Daily Performance - Current'!$I:$I,'Daily Performance - Current'!$B:$B,A3,'Daily Performance - Current'!$E:$E,B3)*D3 | G3: =IFERROR(F3/E3,0) | H3: =SUMIFS('Daily Performance - Current'!$L:$L,'Daily Performance - Current'!$B:$B,A3,'Daily Performance - Current'!$E:$E,B3)*D3
A4: Vantage CRM | B4: LinkedIn | C4: Video | D4: 0.2 | E4: =SUMIFS('Daily Performance - Current'!$H:$H,'Daily Performance - Current'!$B:$B,A4,'Daily Performance - Current'!$E:$E,B4)*D4 | F4: =SUMIFS('Daily Performance - Current'!$I:$I,'Daily Performance - Current'!$B:$B,A4,'Daily Performance - Current'!$E:$E,B4)*D4 | G4: =IFERROR(F4/E4,0) | H4: =SUMIFS('Daily Performance - Current'!$L:$L,'Daily Performance - Current'!$B:$B,A4,'Daily Performance - Current'!$E:$E,B4)*D4
A5: Lumiere Skincare | B5: Instagram | C5: Text | D5: 0.2 | E5: =SUMIFS('Daily Performance - Current'!$H:$H,'Daily Performance - Current'!$B:$B,A5,'Daily Performance - Current'!$E:$E,B5)*D5 | F5: =SUMIFS('Daily Performance - Current'!$I:$I,'Daily Performance - Current'!$B:$B,A5,'Daily Performance - Current'!$E:$E,B5)*D5 | G5: =IFERROR(F5/E5,0) | H5: =SUMIFS('Daily Performance - Current'!$L:$L,'Daily Performance - Current'!$B:$B,A5,'Daily Performance - Current'!$E:$E,B5)*D5
A6: Lumiere Skincare | B6: Instagram | C6: Image | D6: 0.4 | E6: =SUMIFS('Daily Performance - Current'!$H:$H,'Daily Performance - Current'!$B:$B,A6,'Daily Performance - Current'!$E:$E,B6)*D6 | F6: =SUMIFS('Daily Performance - Current'!$I:$I,'Daily Performance - Current'!$B:$B,A6,'Daily Performance - Current'!$E:$E,B6)*D6 | G6: =IFERROR(F6/E6,0) | H6: =SUMIFS('Daily Performance - Current'!$L:$L,'Daily Performance - Current'!$B:$B,A6,'Daily Performance - Current'!$E:$E,B6)*D6
A7: Lumiere Skincare | B7: Instagram | C7: Video | D7: 0.4 | E7: =SUMIFS('Daily Performance - Current'!$H:$H,'Daily Performance - Current'!$B:$B,A7,'Daily Performance - Current'!$E:$E,B7)*D7 | F7: =SUMIFS('Daily Performance - Current'!$I:$I,'Daily Performance - Current'!$B:$B,A7,'Daily Performance - Current'!$E:$E,B7)*D7 | G7: =IFERROR(F7/E7,0) | H7: =SUMIFS('Daily Performance - Current'!$L:$L,'Daily Performance - Current'!$B:$B,A7,'Daily Performance - Current'!$E:$E,B7)*D7
A8: Lumiere Skincare | B8: Facebook | C8: Text | D8: 0.2 | E8: =SUMIFS('Daily Performance - Current'!$H:$H,'Daily Performance - Current'!$B:$B,A8,'Daily Performance - Current'!$E:$E,B8)*D8 | F8: =SUMIFS('Daily Performance - Current'!$I:$I,'Daily Performance - Current'!$B:$B,A8,'Daily Performance - Current'!$E:$E,B8)*D8 | G8: =IFERROR(F8/E8,0) | H8: =SUMIFS('Daily Performance - Current'!$L:$L,'Daily Performance - Current'!$B:$B,A8,'Daily Performance - Current'!$E:$E,B8)*D8
A9: Lumiere Skincare | B9: Facebook | C9: Image | D9: 0.4 | E9: =SUMIFS('Daily Performance - Current'!$H:$H,'Daily Performance - Current'!$B:$B,A9,'Daily Performance - Current'!$E:$E,B9)*D9 | F9: =SUMIFS('Daily Performance - Current'!$I:$I,'Daily Performance - Current'!$B:$B,A9,'Daily Performance - Current'!$E:$E,B9)*D9 | G9: =IFERROR(F9/E9,0) | H9: =SUMIFS('Daily Performance - Current'!$L:$L,'Daily Performance - Current'!$B:$B,A9,'Daily Performance - Current'!$E:$E,B9)*D9
A10: Lumiere Skincare | B10: Facebook | C10: Video | D10: 0.4 | E10: =SUMIFS('Daily Performance - Current'!$H:$H,'Daily Performance - Current'!$B:$B,A10,'Daily Performance - Current'!$E:$E,B10)*D10 | F10: =SUMIFS('Daily Performance - Current'!$I:$I,'Daily Performance - Current'!$B:$B,A10,'Daily Performance - Current'!$E:$E,B10)*D10 | G10: =IFERROR(F10/E10,0) | H10: =SUMIFS('Daily Performance - Current'!$L:$L,'Daily Performance - Current'!$B:$B,A10,'Daily Performance - Current'!$E:$E,B10)*D10
A11: Lumiere Skincare | B11: Pinterest | C11: Text | D11: 0.2 | E11: =SUMIFS('Daily Performance - Current'!$H:$H,'Daily Performance - Current'!$B:$B,A11,'Daily Performance - Current'!$E:$E,B11)*D11 | F11: =SUMIFS('Daily Performance - Current'!$I:$I,'Daily Performance - Current'!$B:$B,A11,'Daily Performance - Current'!$E:$E,B11)*D11 | G11: =IFERROR(F11/E11,0) | H11: =SUMIFS('Daily Performance - Current'!$L:$L,'Daily Performance - Current'!$B:$B,A11,'Daily Performance - Current'!$E:$E,B11)*D11
A12: Lumiere Skincare | B12: Pinterest | C12: Image | D12: 0.4 | E12: =SUMIFS('Daily Performance - Current'!$H:$H,'Daily Performance - Current'!$B:$B,A12,'Daily Performance - Current'!$E:$E,B12)*D12 | F12: =SUMIFS('Daily Performance - Current'!$I:$I,'Daily Performance - Current'!$B:$B,A12,'Daily Performance - Current'!$E:$E,B12)*D12 | G12: =IFERROR(F12/E12,0) | H12: =SUMIFS('Daily Performance - Current'!$L:$L,'Daily Performance - Current'!$B:$B,A12,'Daily Performance - Current'!$E:$E,B12)*D12
A13: Lumiere Skincare | B13: Pinterest | C13: Video | D13: 0.4 | E13: =SUMIFS('Daily Performance - Current'!$H:$H,'Daily Performance - Current'!$B:$B,A13,'Daily Performance - Current'!$E:$E,B13)*D13 | F13: =SUMIFS('Daily Performance - Current'!$I:$I,'Daily Performance - Current'!$B:$B,A13,'Daily Performance - Current'!$E:$E,B13)*D13 | G13: =IFERROR(F13/E13,0) | H13: =SUMIFS('Daily Performance - Current'!$L:$L,'Daily Performance - Current'!$B:$B,A13,'Daily Performance - Current'!$E:$E,B13)*D13
... A21: Aurelia Jewellery | B21: Instagram | C21: Image | D21: 0.4 | E21: =SUMIFS('Daily Performance - Current'!$H:$H,'Daily Performance - Current'!$B:$B,A21,'Daily Performance - Current'!$E:$E,B21)*D21 | F21: =SUMIFS('Daily Performance - Current'!$I:$I,'Daily Performance - Current'!$B:$B,A21,'Daily Performance - Current'!$E:$E,B21)*D21 | G21: =IFERROR(F21/E21,0) | H21: =SUMIFS('Daily Performance - Current'!$L:$L,'Daily Performance - Current'!$B:$B,A21,'Daily Performance - Current'!$E:$E,B21)*D21
A22: Aurelia Jewellery | B22: Instagram | C22: Video | D22: 0.45 | E22: =SUMIFS('Daily Performance - Current'!$H:$H,'Daily Performance - Current'!$B:$B,A22,'Daily Performance - Current'!$E:$E,B22)*D22 | F22: =SUMIFS('Daily Performance - Current'!$I:$I,'Daily Performance - Current'!$B:$B,A22,'Daily Performance - Current'!$E:$E,B22)*D22 | G22: =IFERROR(F22/E22,0) | H22: =SUMIFS('Daily Performance - Current'!$L:$L,'Daily Performance - Current'!$B:$B,A22,'Daily Performance - Current'!$E:$E,B22)*D22 | I22: Required creative type for this product -- luxury storytelling
A23: Aurelia Jewellery | B23: Pinterest | C23: Text | D23: 0.15 | E23: =SUMIFS('Daily Performance - Current'!$H:$H,'Daily Performance - Current'!$B:$B,A23,'Daily Performance - Current'!$E:$E,B23)*D23 | F23: =SUMIFS('Daily Performance - Current'!$I:$I,'Daily Performance - Current'!$B:$B,A23,'Daily Performance - Current'!$E:$E,B23)*D23 | G23: =IFERROR(F23/E23,0) | H23: =SUMIFS('Daily Performance - Current'!$L:$L,'Daily Performance - Current'!$B:$B,A23,'Daily Performance - Current'!$E:$E,B23)*D23
A24: Aurelia Jewellery | B24: Pinterest | C24: Image | D24: 0.4 | E24: =SUMIFS('Daily Performance - Current'!$H:$H,'Daily Performance - Current'!$B:$B,A24,'Daily Performance - Current'!$E:$E,B24)*D24 | F24: =SUMIFS('Daily Performance - Current'!$I:$I,'Daily Performance - Current'!$B:$B,A24,'Daily Performance - Current'!$E:$E,B24)*D24 | G24: =IFERROR(F24/E24,0) | H24: =SUMIFS('Daily Performance - Current'!$L:$L,'Daily Performance - Current'!$B:$B,A24,'Daily Performance - Current'!$E:$E,B24)*D24
A25: Aurelia Jewellery | B25: Pinterest | C25: Video | D25: 0.45 | E25: =SUMIFS('Daily Performance - Current'!$H:$H,'Daily Performance - Current'!$B:$B,A25,'Daily Performance - Current'!$E:$E,B25)*D25 | F25: =SUMIFS('Daily Performance - Current'!$I:$I,'Daily Performance - Current'!$B:$B,A25,'Daily Performance - Current'!$E:$E,B25)*D25 | G25: =IFERROR(F25/E25,0) | H25: =SUMIFS('Daily Performance - Current'!$L:$L,'Daily Performance - Current'!$B:$B,A25,'Daily Performance - Current'!$E:$E,B25)*D25 | I25: Required creative type for this product -- luxury storytelling
A26: Aurelia Jewellery | B26: Google Ads | C26: Text | D26: 0.15 | E26: =SUMIFS('Daily Performance - Current'!$H:$H,'Daily Performance - Current'!$B:$B,A26,'Daily Performance - Current'!$E:$E,B26)*D26 | F26: =SUMIFS('Daily Performance - Current'!$I:$I,'Daily Performance - Current'!$B:$B,A26,'Daily Performance - Current'!$E:$E,B26)*D26 | G26: =IFERROR(F26/E26,0) | H26: =SUMIFS('Daily Performance - Current'!$L:$L,'Daily Performance - Current'!$B:$B,A26,'Daily Performance - Current'!$E:$E,B26)*D26
A27: Aurelia Jewellery | B27: Google Ads | C27: Image | D27: 0.4 | E27: =SUMIFS('Daily Performance - Current'!$H:$H,'Daily Performance - Current'!$B:$B,A27,'Daily Performance - Current'!$E:$E,B27)*D27 | F27: =SUMIFS('Daily Performance - Current'!$I:$I,'Daily Performance - Current'!$B:$B,A27,'Daily Performance - Current'!$E:$E,B27)*D27 | G27: =IFERROR(F27/E27,0) | H27: =SUMIFS('Daily Performance - Current'!$L:$L,'Daily Performance - Current'!$B:$B,A27,'Daily Performance - Current'!$E:$E,B27)*D27
A28: Aurelia Jewellery | B28: Google Ads | C28: Video | D28: 0.45 | E28: =SUMIFS('Daily Performance - Current'!$H:$H,'Daily Performance - Current'!$B:$B,A28,'Daily Performance - Current'!$E:$E,B28)*D28 | F28: =SUMIFS('Daily Performance - Current'!$I:$I,'Daily Performance - Current'!$B:$B,A28,'Daily Performance - Current'!$E:$E,B28)*D28 | G28: =IFERROR(F28/E28,0) | H28: =SUMIFS('Daily Performance - Current'!$L:$L,'Daily Performance - Current'!$B:$B,A28,'Daily Performance - Current'!$E:$E,B28)*D28 | I28: Required creative type for this product -- luxury storytelling

Sheet QoQ Learnings
A1: Product | B1: What We Saw Last Quarter | C1: What We Changed This Quarter | D1: Historical Revenue (INR) | E1: Current Revenue (INR) | F1: % Improvement
A2: Vantage CRM | B2: Static carousel ads underperformed on thought-leadership topics; SQL rate lagged despite decent lead volume. | C2: Shifted budget toward video testimonials and a gated ROI-calculator whitepaper CTA to pull in higher-intent leads. | D2: =SUMIF('Daily Performance - Historical'!$B:$B,A2,'Daily Performance - Historical'!$R:$R) | E2: =SUMIF('Daily Performance - Current'!$B:$B,A2,'Daily Performance - Current'!$R:$R) | F2: =IFERROR((E2-D2)/D2,0)
A3: Lumiere Skincare | B3: Pinterest drove disproportionately high-intent traffic (best conversion rate of the 3 channels) despite the smallest budget share. | C3: Reallocated ~35% of Facebook's budget into Pinterest and added UGC-style short video across all three channels. | D3: =SUMIF('Daily Performance - Historical'!$B:$B,A3,'Daily Performance - Historical'!$R:$R) | E3: =SUMIF('Daily Performance - Current'!$B:$B,A3,'Daily Performance - Current'!$R:$R) | F3: =IFERROR((E3-D3)/D3,0)
A4: Solara Fitband | B4: Generic feature-focused ad copy ('heart-rate tracking', 'GPS built-in') underperformed vs. outcome-focused messaging. | C4: Rewrote all creative around outcomes ('reach your 10K-step goal') and added 15-second product-demo video across both channels. | D4: =SUMIF('Daily Performance - Historical'!$B:$B,A4,'Daily Performance - Historical'!$R:$R) | E4: =SUMIF('Daily Performance - Current'!$B:$B,A4,'Daily Performance - Current'!$R:$R) | F4: =IFERROR((E4-D4)/D4,0)
A5: Aurelia Jewellery | B5: Static product-shot images underperformed for a high-consideration luxury purchase -- low engagement, long time-on-decision. | C5: Introduced cinematic video creative showcasing craftsmanship and provenance storytelling across all three channels. | D5: =SUMIF('Daily Performance - Historical'!$B:$B,A5,'Daily Performance - Historical'!$R:$R) | E5: =SUMIF('Daily Performance - Current'!$B:$B,A5,'Daily Performance - Current'!$R:$R) | F5: =IFERROR((E5-D5)/D5,0)
